snekrpc/__init__.py
snekrpc/__main__.py
snekrpc/cli.py
snekrpc/codec/__init__.py
snekrpc/codec/json.py
snekrpc/codec/msgpack.py
snekrpc/errors.py
snekrpc/formatter/__init__.py
snekrpc/formatter/pretty.py
snekrpc/formatter/standard.py
snekrpc/interface.py
snekrpc/logs.py
snekrpc/pack.py
snekrpc/protocol.py
snekrpc/py.typed
snekrpc/registry.py
snekrpc/service/__init__.py
snekrpc/service/file.py
snekrpc/service/health.py
snekrpc/service/metadata.py
snekrpc/service/remote.py
snekrpc/templates/client.py.j2
snekrpc/transport/__init__.py
snekrpc/transport/http.py
snekrpc/transport/tcp.py
snekrpc/transport/unix.py
snekrpc/utils/__init__.py
snekrpc/utils/format.py
snekrpc/utils/function.py
snekrpc/utils/path.py
snekrpc/utils/retry.py
snekrpc/utils/url.py
snekrpc-0.8.0.dist-info/WHEEL
snekrpc-0.8.0.dist-info/entry_points.txt
snekrpc-0.8.0.dist-info/METADATA
snekrpc-0.8.0.dist-info/RECORD
