Metadata-Version: 2.3
Name: snekrpc
Version: 0.8.0
Requires-Dist: makefun>=1.16.0
Requires-Dist: msgpack>=1.0.8
Requires-Dist: msgspec>=0.19.0
Requires-Python: >=3.11
